acore_server_monitoring_core/__init__.py
acore_server_monitoring_core/_version.py
acore_server_monitoring_core/api.py
acore_server_monitoring_core/dynamodb.py
acore_server_monitoring_core/paths.py
acore_server_monitoring_core/docs/__init__.py
acore_server_monitoring_core/tests/__init__.py
acore_server_monitoring_core/tests/helper.py
acore_server_monitoring_core/vendor/__init__.py
acore_server_monitoring_core/vendor/pytest_cov_helper.py
acore_server_monitoring_core-0.1.2.dist-info/AUTHORS.rst
acore_server_monitoring_core-0.1.2.dist-info/LICENSE.txt
acore_server_monitoring_core-0.1.2.dist-info/METADATA
acore_server_monitoring_core-0.1.2.dist-info/WHEEL
acore_server_monitoring_core-0.1.2.dist-info/top_level.txt
acore_server_monitoring_core-0.1.2.dist-info/RECORD
